recsplain/__init__.py
recsplain/__main__.py
recsplain/encoders.py
recsplain/endpoint.py
recsplain/similarity_helpers.py
recsplain/strategies.py
recsplain/tree_helpers.py
recsplain-0.0.55.dist-info/METADATA
recsplain-0.0.55.dist-info/WHEEL
recsplain-0.0.55.dist-info/top_level.txt
recsplain-0.0.55.dist-info/RECORD
