Metadata-Version: 2.1
Name: recsplain
Version: 0.0.55
Home-page: https://github.com/argmaxml/recsplain
Author: ArgmaxML
Author-email: uri@argmax.ml
Keywords: recommendation-systems,recsys,matching,ranking
Requires-Dist: faiss-cpu (>=1.7.1.post3)
Requires-Dist: hnswlib (>=0.5.1)
Requires-Dist: numpy (>=1.21.2)
Requires-Dist: fastapi (>=0.68.0)
Requires-Dist: uvicorn (>=0.15.0)
Requires-Dist: smart-open[s3] (~=3.0.0)
Requires-Dist: joblib (>=0.17.0)
Requires-Dist: tqdm (>=4.62.3)
Requires-Dist: pandas (>=1.3.0)
